python3ptbr/__init__.py
python3ptbr/__main__.py
python3ptbr/cli.py
python3ptbr-1.2.0.dist-info/LICENSE
python3ptbr-1.2.0.dist-info/METADATA
python3ptbr-1.2.0.dist-info/WHEEL
python3ptbr-1.2.0.dist-info/entry_points.txt
python3ptbr-1.2.0.dist-info/top_level.txt
python3ptbr-1.2.0.dist-info/RECORD
